lightmcp/__init__.py
lightmcp/cli.py
lightmcp/tool_loader.py
lightmcp/tool_registry.json
lightmcp-0.1.4.dist-info/licenses/LICENSE
lightmcp-0.1.4.dist-info/METADATA
lightmcp-0.1.4.dist-info/WHEEL
lightmcp-0.1.4.dist-info/entry_points.txt
lightmcp-0.1.4.dist-info/top_level.txt
lightmcp-0.1.4.dist-info/RECORD
