Metadata-Version: 2.4
Name: lightmcp
Version: 0.1.4
Summary: A lightweight MCP tool layer for LLM agent frameworks.
Author-email: Gök Bora Yılmaz <gokbora@lightmcp.dev>
License: MIT
Classifier: Programming Language :: Python :: 3
Classifier: License :: OSI Approved :: MIT License
Classifier: Development Status :: 2 - Pre-Alpha
Classifier: Intended Audience :: Developers
Classifier: Topic :: Software Development :: Libraries
Requires-Python: >=3.9
License-File: LICENSE
Requires-Dist: fastmcp>=2.0.0
Requires-Dist: requests>=2.25.0
Provides-Extra: notion
Requires-Dist: notion-client>=1.0.0; extra == "notion"
Provides-Extra: github
Requires-Dist: requests>=2.25.0; extra == "github"
Provides-Extra: all
Requires-Dist: notion-client>=1.0.0; extra == "all"
Requires-Dist: requests>=2.25.0; extra == "all"
Dynamic: license-file
